{"license": "http://licence", "sequences": [{"viewingDirection": "left-to-right", "canvases": [{"thumbnail": "https://american-art.github.io/iiif\\thumbnails\\puam\\C1303_Bx9_F2006.jpg", "height": 1453, "width": 1999, "images": [{"resource": {"service": {"profile": "http://iiif.io/api/image/2/level1.json", "@context": "http://iiif.io/api/image/2/context.json", "@id": "http://artimage.princeton.edu/files/ProductionJpegs/C1303_Bx9_F2006.jpg"}, "format": "image/jpeg", "height": 1453, "width": 1999, "@id": "http://artimage.princeton.edu/files/ProductionJpegs/C1303_Bx9_F2006.jpg", "@type": "dctypes:Image"}, "on": "https:/artimage.princeton.edu/files/ProductionJpegs/canvas/C1303_Bx9_F2006.jpg", "motivation": "sc:painting", "@id": "https:/artimage.princeton.edu/files/ProductionJpegs/annotation/C1303_Bx9_F2006.jpg", "@type": "oa:Annotation"}], "label": "Untitled [New York and Empire State Building, as seen from New Jersey]", "@id": "https:/artimage.princeton.edu/files/ProductionJpegs/canvas/C1303_Bx9_F2006.jpg", "@type": "sc:Canvas"}], "@id": "https://american-art.github.io/iiif/sequence/wpY9ahjj65ZHPQ8X/0", "@type": "sc:Sequence", "label": "Sequence 1"}], "@context": "http://iiif.io/api/presentation/2/context.json", "seealso": {"@id": "http://data.americanartcollaborative.org/puam/object/85142", "format": "text/rdf"}, "@id": "https://american-art.github.io/iiif/manifest/puam/C1303_Bx9_F2006.json", "@type": "sc:Manifest", "structures": [], "label": "Untitled [New York and Empire State Building, as seen from New Jersey]"}