{"license": "http://licence", "sequences": [{"viewingDirection": "left-to-right", "canvases": [{"thumbnail": "https://american-art.github.io/iiif\\thumbnails\\puam\\INV18792.jpg", "height": 2000, "width": 1274, "images": [{"resource": {"service": {"profile": "http://iiif.io/api/image/2/level1.json", "@context": "http://iiif.io/api/image/2/context.json", "@id": "http://artimage.princeton.edu/files/ProductionJpegs/INV18792.jpg"}, "format": "image/jpeg", "height": 2000, "width": 1274, "@id": "http://artimage.princeton.edu/files/ProductionJpegs/INV18792.jpg", "@type": "dctypes:Image"}, "on": "https:/artimage.princeton.edu/files/ProductionJpegs/canvas/INV18792.jpg", "motivation": "sc:painting", "@id": "https:/artimage.princeton.edu/files/ProductionJpegs/annotation/INV18792.jpg", "@type": "oa:Annotation"}], "label": "An Italian-American owned business or residences in Brooklyn, New York", "@id": "https:/artimage.princeton.edu/files/ProductionJpegs/canvas/INV18792.jpg", "@type": "sc:Canvas"}], "@id": "https://american-art.github.io/iiif/sequence/wpY9ahjj65ZHPQ8X/0", "@type": "sc:Sequence", "label": "Sequence 1"}], "@context": "http://iiif.io/api/presentation/2/context.json", "seealso": {"@id": "http://data.americanartcollaborative.org/puam/object/58319", "format": "text/rdf"}, "@id": "https://american-art.github.io/iiif/manifest/puam/INV18792.json", "@type": "sc:Manifest", "structures": [], "label": "An Italian-American owned business or residences in Brooklyn, New York"}