{"license": "http://licence", "sequences": [{"viewingDirection": "left-to-right", "canvases": [{"thumbnail": "https://american-art.github.io/iiif\\thumbnails\\puam\\INV47656.jpg", "height": 3415, "width": 3396, "images": [{"resource": {"service": {"profile": "http://iiif.io/api/image/2/level1.json", "@context": "http://iiif.io/api/image/2/context.json", "@id": "http://artimage.princeton.edu/files/ProductionJpegs/INV47656.jpg"}, "format": "image/jpeg", "height": 3415, "width": 3396, "@id": "http://artimage.princeton.edu/files/ProductionJpegs/INV47656.jpg", "@type": "dctypes:Image"}, "on": "https:/artimage.princeton.edu/files/ProductionJpegs/canvas/INV47656.jpg", "motivation": "sc:painting", "@id": "https:/artimage.princeton.edu/files/ProductionJpegs/annotation/INV47656.jpg", "@type": "oa:Annotation"}], "label": "A.E.A.A. Algamatant", "@id": "https:/artimage.princeton.edu/files/ProductionJpegs/canvas/INV47656.jpg", "@type": "sc:Canvas"}], "@id": "https://american-art.github.io/iiif/sequence/wpY9ahjj65ZHPQ8X/0", "@type": "sc:Sequence", "label": "Sequence 1"}], "@context": "http://iiif.io/api/presentation/2/context.json", "seealso": {"@id": "http://data.americanartcollaborative.org/puam/object/36423", "format": "text/rdf"}, "@id": "https://american-art.github.io/iiif/manifest/puam/INV47656.json", "@type": "sc:Manifest", "structures": [], "label": "A.E.A.A. Algamatant"}