{"license": "http://licence", "sequences": [{"viewingDirection": "left-to-right", "canvases": [{"thumbnail": "https://american-art.github.io/iiif\\thumbnails\\puam\\INV62718.jpg", "height": 2140, "width": 2546, "images": [{"resource": {"service": {"profile": "http://iiif.io/api/image/2/level1.json", "@context": "http://iiif.io/api/image/2/context.json", "@id": "http://artimage.princeton.edu/files/ProductionJpegs/INV62718.jpg"}, "format": "image/jpeg", "height": 2140, "width": 2546, "@id": "http://artimage.princeton.edu/files/ProductionJpegs/INV62718.jpg", "@type": "dctypes:Image"}, "on": "https:/artimage.princeton.edu/files/ProductionJpegs/canvas/INV62718.jpg", "motivation": "sc:painting", "@id": "https:/artimage.princeton.edu/files/ProductionJpegs/annotation/INV62718.jpg", "@type": "oa:Annotation"}], "label": "unknown", "@id": "https:/artimage.princeton.edu/files/ProductionJpegs/canvas/INV62718.jpg", "@type": "sc:Canvas"}], "@id": "https://american-art.github.io/iiif/sequence/wpY9ahjj65ZHPQ8X/0", "@type": "sc:Sequence", "label": "Sequence 1"}], "@context": "http://iiif.io/api/presentation/2/context.json", "seealso": {"@id": "http://data.americanartcollaborative.org/puam/object/51286", "format": "text/rdf"}, "@id": "https://american-art.github.io/iiif/manifest/puam/INV62718.json", "@type": "sc:Manifest", "structures": [], "label": "unknown"}