{"license": "http://licence", "sequences": [{"viewingDirection": "left-to-right", "canvases": [{"thumbnail": "https://american-art.github.io/iiif\\thumbnails\\puam\\LA_PLATE_REACH1.jpg", "height": 780, "width": 1024, "images": [{"resource": {"service": {"profile": "http://iiif.io/api/image/2/level1.json", "@context": "http://iiif.io/api/image/2/context.json", "@id": "http://artimage.princeton.edu/files/ProductionJpegs/LA_PLATE_REACH1.jpg"}, "format": "image/jpeg", "height": 780, "width": 1024, "@id": "http://artimage.princeton.edu/files/ProductionJpegs/LA_PLATE_REACH1.jpg", "@type": "dctypes:Image"}, "on": "https:/artimage.princeton.edu/files/ProductionJpegs/canvas/LA_PLATE_REACH1.jpg", "motivation": "sc:painting", "@id": "https:/artimage.princeton.edu/files/ProductionJpegs/annotation/LA_PLATE_REACH1.jpg", "@type": "oa:Annotation"}], "label": "Banning Street", "@id": "https:/artimage.princeton.edu/files/ProductionJpegs/canvas/LA_PLATE_REACH1.jpg", "@type": "sc:Canvas"}], "@id": "https://american-art.github.io/iiif/sequence/wpY9ahjj65ZHPQ8X/0", "@type": "sc:Sequence", "label": "Sequence 1"}], "@context": "http://iiif.io/api/presentation/2/context.json", "seealso": {"@id": "http://data.americanartcollaborative.org/puam/object/103010", "format": "text/rdf"}, "@id": "https://american-art.github.io/iiif/manifest/puam/LA_PLATE_REACH1.json", "@type": "sc:Manifest", "structures": [], "label": "Banning Street"}