{"license": "http://licence", "sequences": [{"viewingDirection": "left-to-right", "canvases": [{"thumbnail": "https://american-art.github.io/iiif\\thumbnails\\puam\\y1969-8_ver_b.jpg", "height": 2000, "width": 1635, "images": [{"resource": {"service": {"profile": "http://iiif.io/api/image/2/level1.json", "@context": "http://iiif.io/api/image/2/context.json", "@id": "http://artimage.princeton.edu/files/ProductionJpegs/y1969-8_ver_b.jpg"}, "format": "image/jpeg", "height": 2000, "width": 1635, "@id": "http://artimage.princeton.edu/files/ProductionJpegs/y1969-8_ver_b.jpg", "@type": "dctypes:Image"}, "on": "https:/artimage.princeton.edu/files/ProductionJpegs/canvas/y1969-8_ver_b.jpg", "motivation": "sc:painting", "@id": "https:/artimage.princeton.edu/files/ProductionJpegs/annotation/y1969-8_ver_b.jpg", "@type": "oa:Annotation"}], "label": "Model for Atmosphere and Environment X", "@id": "https:/artimage.princeton.edu/files/ProductionJpegs/canvas/y1969-8_ver_b.jpg", "@type": "sc:Canvas"}], "@id": "https://american-art.github.io/iiif/sequence/wpY9ahjj65ZHPQ8X/0", "@type": "sc:Sequence", "label": "Sequence 1"}], "@context": "http://iiif.io/api/presentation/2/context.json", "seealso": {"@id": "http://data.americanartcollaborative.org/puam/object/31309", "format": "text/rdf"}, "@id": "https://american-art.github.io/iiif/manifest/puam/y1969-8_ver_b.json", "@type": "sc:Manifest", "structures": [], "label": "Model for Atmosphere and Environment X"}