{"label": "Lost and Found", "sequences": [{"viewingDirection": "left-to-right", "canvases": [{"thumbnail": "https://american-art.github.io/iiif/thumbnails/gm/01.2543_o6.jpg", "height": 750, "width": 978, "images": [{"resource": {"format": "image/jpeg", "height": 750, "width": 978, "@id": "https://gm-piction-live.s3.amazonaws.com/styles/primary_asset/s3/assets/01.2543_o6.jpg", "@type": "dctypes:Image"}, "on": "https:/gm-piction-live.s3.amazonaws.com/styles/primary_asset/s3/assets/canvas/01.2543_o6.jpg", "motivation": "sc:painting", "@id": "https:/gm-piction-live.s3.amazonaws.com/styles/primary_asset/s3/assets/annotation/01.2543_o6.jpg", "@type": "oa:Annotation"}], "label": "Lost and Found", "@id": "https:/gm-piction-live.s3.amazonaws.com/styles/primary_asset/s3/assets/canvas/01.2543_o6.jpg", "@type": "sc:Canvas"}], "@id": "https://american-art.github.io/iiif/sequence/JTML33w7xdkVOEQJ/0", "@type": "sc:Sequence", "label": "Sequence 1"}], "@context": "http://iiif.io/api/presentation/2/context.json", "@id": "https://american-art.github.io/iiif/manifest/gm/01.2543_o6.json", "@type": "sc:Manifest", "seeAlso": {"@id": "http://data.americanartcollaborative.org/GM/object/13203", "format": "text/rdf"}}