{"structures": [], "label": "Cathedral, Side", "sequences": [{"viewingDirection": "left-to-right", "canvases": [{"width": 1546, "metadata": [{"value": "Cathedral, Side", "label": "caption"}], "license": "http://licence", "images": [{"resource": {"service": {"@id": "http://artimage.princeton.edu/files/ProductionJpegs/INV29409.jpg"}, "format": "image/jpeg", "height": 2000, "width": 1546, "@id": "http://artimage.princeton.edu/files/ProductionJpegs/INV29409.jpg/full/full/0/native.jpg", "@type": "dctypes:Image"}, "on": "https:/artimage.princeton.edu/files/ProductionJpegs/canvas/INV29409.jpg", "motivation": "sc:painting", "@id": "https:/artimage.princeton.edu/files/ProductionJpegs/annotation/INV29409.jpg", "@type": "oa:Annotation"}], "thumbnail": "data:image/jpeg;base64,", "height": 2000, "@id": "https:/artimage.princeton.edu/files/ProductionJpegs/canvas/INV29409.jpg", "@type": "sc:Canvas", "label": "Cathedral, Side"}], "@id": "https://jainn3.github.io/iiif-manifest-museum-II/sequence/KcO77iTqD76eesyi/0", "@type": "sc:Sequence", "label": "Sequence 1"}], "@context": "http://iiif.io/api/presentation/2/context.json", "@id": "https://jainn3.github.io/iiif-manifest-museum-II/manifest/Uk3PReTRZ96NGHrI", "@type": "sc:Manifest", "seealso": {"@id": "http://data.americanartcollaborative.org/puam/object/13738", "format": "text/rdf"}}