{"license": "http://licence", "sequences": [{"viewingDirection": "left-to-right", "canvases": [{"thumbnail": "https://american-art.github.io/iiif\\thumbnails\\ima\\63229.jpg", "height": 329, "width": 600, "images": [{"resource": {"service": {"profile": "http://iiif.io/api/image/2/level1.json", "@context": "http://iiif.io/api/image/2/context.json", "@id": "http://collection.imamuseum.org/artwork/63229/0_full.jpg"}, "format": "image/jpeg", "height": 329, "width": 600, "@id": "http://collection.imamuseum.org/artwork/63229/0_full.jpg", "@type": "dctypes:Image"}, "on": "https:/collection.imamuseum.org/artwork/63229/canvas/0_full.jpg", "motivation": "sc:painting", "@id": "https:/collection.imamuseum.org/artwork/63229/annotation/0_full.jpg", "@type": "oa:Annotation"}], "label": "Wheat-wain, Study for Wheat-wain Afield", "@id": "https:/collection.imamuseum.org/artwork/63229/canvas/0_full.jpg", "@type": "sc:Canvas"}], "@id": "https://american-art.github.io/iiif/sequence/wpY9ahjj65ZHPQ8X/0", "@type": "sc:Sequence", "label": "Sequence 1"}], "@context": "http://iiif.io/api/presentation/2/context.json", "seealso": {"@id": "http://data.americanartcollaborative.org/ima/object/44352", "format": "text/rdf"}, "@id": "https://american-art.github.io/iiif/manifest/ima/63229.json", "@type": "sc:Manifest", "structures": [], "label": "Wheat-wain, Study for Wheat-wain Afield"}