{"structures": [], "label": "Red China", "sequences": [{"viewingDirection": "left-to-right", "canvases": [], "@id": "https://jainn3.github.io/iiif-manifest-museum-II/sequence/VPC1gulTpXVSP52H/0", "@type": "sc:Sequence", "label": "Sequence 1"}], "@context": "http://iiif.io/api/presentation/2/context.json", "@id": "https://jainn3.github.io/iiif-manifest-museum-II/manifest/D1z1WD9j1fyT1Kep", "@type": "sc:Manifest", "seealso": {"@id": "http://data.americanartcollaborative.org/npg/object/49439", "format": "text/rdf"}}