{"structures": [], "label": "Joshua Daniel White", "sequences": [{"viewingDirection": "left-to-right", "canvases": [], "@id": "https://jainn3.github.io/iiif-manifest-museum-II/sequence/2mpQHuBLTWED6dxQ/0", "@type": "sc:Sequence", "label": "Sequence 1"}], "@context": "http://iiif.io/api/presentation/2/context.json", "@id": "https://jainn3.github.io/iiif-manifest-museum-II/manifest/O0GJfaItl0FLnsZn", "@type": "sc:Manifest", "seealso": {"@id": "http://data.americanartcollaborative.org/npg/object/52320", "format": "text/rdf"}}